{
  "Id": 13,
  "Name": "New Workflow",
  "Description": "",
  "IsDebug": false,
  "ActionList": {
    "Id": 17,
    "EventName": "Event",
    "Actions": [
      {
        "Id": 14,
        "Description": "",
        "ActionErrorMessage": "",
        "Condition": "",
        "ActionType": "CopyFile",
        "OrderIndex": 0,
        "ActionParameters": [],
        "DiagramUID": "Activity_0s9pyz4"
      }
    ]
  },
  "CreatedBy": "SuperUser Account",
  "CreatedOn": "2020-11-05T12:15:14.7024866+02:00",
  "LastModifiedBy": "SuperUser Account",
  "LastModifiedOn": "2020-11-05T12:15:14.7024866+02:00",
  "InputFields": [],
  "OutputFields": []
}